codesmith/__init__.py
codesmith/eval.py
codesmith/python.py
codesmith/read.py
codesmith/wrapper.py
codesmith-0.0.1.dist-info/LICENSE
codesmith-0.0.1.dist-info/METADATA
codesmith-0.0.1.dist-info/WHEEL
codesmith-0.0.1.dist-info/top_level.txt
codesmith-0.0.1.dist-info/RECORD
